libhans-0.1.8.dist-info/METADATA
libhans-0.1.8.dist-info/WHEEL
libhans/__init__.py
libhans/__init__.pyi
libhans/libhans.cp313-win32.pyd
libhans/py.typed
libhans-0.1.8.dist-info/RECORD
