Metadata-Version: 2.4
Name: libhans
Version: 0.1.8
Summary: Rust bindings for the Hans robot
Keywords: hans,robot
Author: Yixing <yanjizhou312@163.com>
Author-email: Yixing <yanjizhou312@163.com>
License: Apache-2.0
Project-URL: Source Code, https://github.com/Robot-Exp-Platform/libhans-rs
